custom_openai/__init__.py
custom_openai/client.py
fq_test_release-0.8.0.dist-info/licenses/LICENSE
fq_test_release-0.8.0.dist-info/METADATA
fq_test_release-0.8.0.dist-info/WHEEL
fq_test_release-0.8.0.dist-info/top_level.txt
fq_test_release-0.8.0.dist-info/RECORD
